casoar/__init__.py
casoar/cli.py
casoar/main.py
casoar/models/__init__.py
casoar/models/command.py
casoar/models/hook.py
casoar/writer.py
casoar-0.1.3.dist-info/METADATA
casoar-0.1.3.dist-info/WHEEL
casoar-0.1.3.dist-info/entry_points.txt
casoar-0.1.3.dist-info/RECORD
