Metadata-Version: 2.1
Name: casoar
Version: 0.1.3
Summary: Git hooks made easy with local dev dependencies
License: MIT
Author: Jocelyn Gas
Author-email: jocelyn.gas@dillygence.com
Requires-Python: >=3.10,<4.0
Classifier: License :: OSI Approved :: MIT License
Classifier: Programming Language :: Python :: 3
Classifier: Programming Language :: Python :: 3.10
Classifier: Programming Language :: Python :: 3.11
Classifier: Programming Language :: Python :: 3.12
Requires-Dist: pydantic (>=2.6.1,<3.0.0)
Requires-Dist: rich (>=13.7.0,<14.0.0)
Requires-Dist: tomlkit (>=0.12.3,<0.13.0)
Requires-Dist: typer (>=0.9.0,<0.10.0)
